django_gatehouse3-1.0.0.dist-info/METADATA
django_gatehouse3-1.0.0.dist-info/RECORD
django_gatehouse3-1.0.0.dist-info/WHEEL
django_gatehouse3-1.0.0.dist-info/top_level.txt
gatehouseapp/__init__.py
gatehouseapp/admin.py
gatehouseapp/apps.py
gatehouseapp/filters.py
gatehouseapp/forms.py
gatehouseapp/models.py
gatehouseapp/tests.py
gatehouseapp/urls.py
gatehouseapp/views.py
gatehouseapp/migrations/0001_initial.py
gatehouseapp/migrations/__init__.py
gatehouseapp/templates/__init__.py
gatehouseapp/templates/gatehouseapp/__init__.py
gatehouseapp/templates/registration/__init__.py
