Metadata-Version: 2.1
Name: django-gatehouse3
Version: 1.0.0
Summary: A simple Django app to create gatehouse Web app.
Home-page: https://github.com/aulemasa/gatehouse3
Author: Aulemasa
Author-email: maszs@wp.pl
License: UNKNOWN
Platform: UNKNOWN
Classifier: Programming Language :: Python :: 3
Classifier: License :: OSI Approved :: GNU General Public License v3 (GPLv3)
Classifier: Operating System :: OS Independent
